<?xml version="1.0"?>
<evolvotron-image-function version="0.6.3" zsweep="sinusoidal" projection="planar">
  <f>
    <type>FunctionTop</type>
    <p>0</p>
    <p>0</p>
    <p>0</p>
    <p>0.49283</p>
    <p>0.186043</p>
    <p>0</p>
    <p>-0.186043</p>
    <p>0.49283</p>
    <p>0</p>
    <p>0</p>
    <p>0</p>
    <p>-10.2739</p>
    <p>1.57806</p>
    <p>-0.144262</p>
    <p>-1.63404</p>
    <p>4.57812</p>
    <p>1.63494</p>
    <p>-0.0368714</p>
    <p>-0.402403</p>
    <p>2.6486</p>
    <p>2.92453</p>
    <p>1.90233</p>
    <p>1.30027</p>
    <p>1</p>
    <f>
      <type>FunctionSeparateZ</type>
      <p>1.71448</p>
      <p>-2.53402</p>
      <p>-3.16997</p>
      <f>
        <type>FunctionFriezeGroupJumpBlendClampZ</type>
        <p>0.925471</p>
        <f>
          <type>FunctionRotate</type>
          <f>
            <type>FunctionTransform</type>
            <p>0.126376</p>
            <p>-0.273195</p>
            <p>-1.59421</p>
            <p>-1.69856</p>
            <p>5.43883</p>
            <p>2.22851</p>
            <p>3.9274</p>
            <p>-0.0426427</p>
            <p>-2.11604</p>
            <p>2.22392</p>
            <p>0.21002</p>
            <p>0.219879</p>
          </f>
        </f>
        <f>
          <type>FunctionTransform</type>
          <p>-0.967249</p>
          <p>-1.99278</p>
          <p>-1.18041</p>
          <p>0.22755</p>
          <p>-1.9221</p>
          <p>1.57353</p>
          <p>-1.85702</p>
          <p>-0.172128</p>
          <p>2.47212</p>
          <p>-0.896516</p>
          <p>0.853551</p>
          <p>-2.82724</p>
        </f>
      </f>
      <f>
        <type>FunctionFriezeGroupHopBlendFreeZ</type>
        <f>
          <type>FunctionFriezeGroupSpinsidleClampZ</type>
          <p>-0.999528</p>
          <f>
            <type>FunctionComposePair</type>
            <f>
              <type>FunctionSpiralLogarithmic</type>
              <f>
                <type>FunctionMultiscaleNoiseOneChannel</type>
              </f>
            </f>
            <f>
              <type>FunctionTransform</type>
              <p>-1.13128</p>
              <p>-0.10536</p>
              <p>0.812547</p>
              <p>-3.328</p>
              <p>-2.94107</p>
              <p>-0.419689</p>
              <p>1.57522</p>
              <p>-0.106282</p>
              <p>0.852866</p>
              <p>-2.09746</p>
              <p>1.91572</p>
              <p>-2.51173</p>
            </f>
          </f>
        </f>
        <f>
          <type>FunctionTransform</type>
          <p>0.680876</p>
          <p>-0.516728</p>
          <p>0.383576</p>
          <p>0.293109</p>
          <p>1.99633</p>
          <p>-2.5675</p>
          <p>-1.72284</p>
          <p>-4.04667</p>
          <p>-1.30104</p>
          <p>1.36149</p>
          <p>0.881268</p>
          <p>0.107806</p>
        </f>
      </f>
    </f>
  </f>
</evolvotron-image-function>
